README
setup.py
nannou/__init__.py
nannou.egg-info/PKG-INFO
nannou.egg-info/SOURCES.txt
nannou.egg-info/dependency_links.txt
nannou.egg-info/top_level.txt