Metadata-Version: 1.0
Name: nannou
Version: 0.7.1
Summary: Compiling template engine based on pattern matching
Home-page: http://packages.python.org/nannou
Author: Niel Faccly
Author-email: nyufac@gmail.com
License: BSD
Keywords: python web templates
Platform: UNKNOWN
Classifier: Development Status :: 3 - Alpha
Classifier: Topic :: Utilities
Classifier: License :: OSI Approved :: BSD License
